[{"model": "fin.voucherkind", "pk": 1, "fields": {"name": "الرواتب الشهرية", "description": "", "ordering": 0, "slug": "الرواتب-الشهرية"}}, {"model": "fin.voucherkind", "pk": 2, "fields": {"name": "الساعات التدريسية للمفرغين جزئياً", "description": "", "ordering": 0, "slug": "الساعات-التدريسية-للمفرغين-جزئيا"}}, {"model": "fin.voucherkind", "pk": 3, "fields": {"name": "الساعات التدريسية لأعضاء الهيئة التدريسية (اضافي)", "description": "", "ordering": 0, "slug": "الساعات-التدريسية-لأعضاء-الهيئة-التدريسية-اضافي"}}, {"model": "fin.voucherkind", "pk": 4, "fields": {"name": "الساعات التدريسية (المكافآت)", "description": "", "ordering": 0, "slug": "الساعات-التدريسية-المكافآت"}}, {"model": "fin.voucherkind", "pk": 5, "fields": {"name": "مكافآت تشجيعية", "description": "", "ordering": 0, "slug": "مكافآت-تشجيعية"}}, {"model": "fin.voucherkind", "pk": 6, "fields": {"name": "مهمات سفر", "description": "", "ordering": 0, "slug": "مهمات-سفر"}}, {"model": "fin.voucherkind", "pk": 7, "fields": {"name": "التأمينات الاجتماعية", "description": "", "ordering": 0, "slug": "التأمينات-الاجتماعية"}}, {"model": "fin.voucherkind", "pk": 8, "fields": {"name": "أيام العمل الاضافي (إداريين)", "description": "", "ordering": 0, "slug": "أيام-العمل-الاضافي-إداريين"}}]